doc2tei/__init__.py
doc2tei/__main__.py
doc2tei/resources/saxon9.jar
doc2tei/resources/schema/metopes.rng
doc2tei/resources/schema/openedition.rng
doc2tei/resources/xsl-01-cleanup/.gitkeep
doc2tei/resources/xsl-01-cleanup/cleanup-delete.xsl
doc2tei/resources/xsl-01-cleanup/cleanup-nodes.xsl
doc2tei/resources/xsl-01-cleanup/cleanup-preserve.xsl
doc2tei/resources/xsl-01-cleanup/cleanup-styles.xsl
doc2tei/resources/xsl-01-cleanup/cleanup.xsl
doc2tei/resources/xsl-02-normalisation/a-normalize-stylename.xsl
doc2tei/resources/xsl-02-normalisation/b-normalize-nodes-cit.xsl
doc2tei/resources/xsl-02-normalisation/b-normalize-nodes-index.xsl
doc2tei/resources/xsl-02-normalisation/b-normalize-nodes.xsl
doc2tei/resources/xsl-02-normalisation/c-normalize-groupspan.xsl
doc2tei/resources/xsl-03-enrich/enrich.xsl
doc2tei/resources/xsl-04-group/group-cit.xsl
doc2tei/resources/xsl-04-group/group-figure-grp.xsl
doc2tei/resources/xsl-04-group/group-figure.xsl
doc2tei/resources/xsl-04-group/group-floatingText.xsl
doc2tei/resources/xsl-04-group/group-review.xsl
doc2tei/resources/xsl-04-group/group-sp.xsl
doc2tei/resources/xsl-04-group/hierarchize-floatingText.xsl
doc2tei/resources/xsl-04-group/hierarchize-review.xsl
doc2tei/resources/xsl-05-control/control-errors.xsl
doc2tei/resources/xsl-05-control/control-hierarchy.xsl
doc2tei/resources/xsl-05-control/control-styles-id.xsl
doc2tei/resources/xsl-06-hierarchize/hierarchize.xsl
doc2tei/resources/xsl-07-organise/organise.xsl
doc2tei/resources/xsl-08-totei/back.xsl
doc2tei/resources/xsl-08-totei/core_cit.xsl
doc2tei/resources/xsl-08-totei/core_code.xsl
doc2tei/resources/xsl-08-totei/core_div-para.xsl
doc2tei/resources/xsl-08-totei/core_figure.xsl
doc2tei/resources/xsl-08-totei/core_linking.xsl
doc2tei/resources/xsl-08-totei/core_list.xsl
doc2tei/resources/xsl-08-totei/core_note.xsl
doc2tei/resources/xsl-08-totei/core_typo.xsl
doc2tei/resources/xsl-08-totei/front.xsl
doc2tei/resources/xsl-08-totei/teiHeader.xsl
doc2tei_certic-0.0.104.dist-info/METADATA
doc2tei_certic-0.0.104.dist-info/WHEEL
doc2tei_certic-0.0.104.dist-info/entry_points.txt
doc2tei_certic-0.0.104.dist-info/RECORD
