Metadata-Version: 2.4
Name: doc2tei-CERTIC
Version: 0.0.104
Summary: Convert ODT and DOCX files to TEI
License: CECILL-C
Author: Edith Cannet
Author-email: edith.cannet@unicaen.fr
Requires-Python: >=3.9,<4.0
Classifier: License :: CeCILL-C Free Software License Agreement (CECILL-C)
Classifier: Programming Language :: Python :: 3
Classifier: Programming Language :: Python :: 3.9
Classifier: Programming Language :: Python :: 3.10
Classifier: Programming Language :: Python :: 3.11
Classifier: Programming Language :: Python :: 3.12
Classifier: Programming Language :: Python :: 3.13
Classifier: Programming Language :: Python :: 3.14
Requires-Dist: argh (>=0.29.4)
